curatedmetagenomicdataloader/__init__.py
curatedmetagenomicdataloader/loader.py
curatedmetagenomicdataloader/loader_test.py
curatedmetagenomicdataloader/metadata.py
curatedmetagenomicdataloader-0.1.3.dist-info/LICENSE
curatedmetagenomicdataloader-0.1.3.dist-info/WHEEL
curatedmetagenomicdataloader-0.1.3.dist-info/METADATA
curatedmetagenomicdataloader-0.1.3.dist-info/RECORD
