Metadata-Version: 2.1
Name: curatedmetagenomicdataloader
Version: 0.1.3
Summary: PyTorch DataLoader for curatedMetagenomicData
License: MIT
Author: smk508
Author-email: skhan8@mail.einstein.yu.edu
Requires-Python: >=3.6,<4.0
Classifier: License :: OSI Approved :: MIT License
Classifier: Programming Language :: Python :: 3
Classifier: Programming Language :: Python :: 3.6
Classifier: Programming Language :: Python :: 3.7
Classifier: Programming Language :: Python :: 3.8
Requires-Dist: biopython (>=1.74,<2.0)
Requires-Dist: fireworks-ml (>=0.3.7,<0.4.0)
Requires-Dist: joblib (>=0.14.1,<0.15.0)
Requires-Dist: psycopg2-binary (>=2.8.4,<3.0.0)
Requires-Dist: python-dotenv (>=0.10.3,<0.11.0)
Requires-Dist: the-whole-caboodle (>=0.1.6,<0.2.0)
Requires-Dist: tqdm (>=4.41.1,<5.0.0)
